LICENSE
MANIFEST.in
README.md
setup.cfg
setup.py
jupyter_kite/__init__.py
jupyter_kite/_version.py
jupyter_kite/constants.py
jupyter_kite/handlers.py
jupyter_kite/locator.py
jupyter_kite/manager.py
jupyter_kite/non_blocking.py
jupyter_kite/onboarding.py
jupyter_kite/paths.py
jupyter_kite/serverextension.py
jupyter_kite/session.py
jupyter_kite/stdio.py
jupyter_kite/trait_types.py
jupyter_kite/types.py
jupyter_kite/virtual_documents_shadow.py
jupyter_kite.egg-info/PKG-INFO
jupyter_kite.egg-info/SOURCES.txt
jupyter_kite.egg-info/dependency_links.txt
jupyter_kite.egg-info/entry_points.txt
jupyter_kite.egg-info/not-zip-safe
jupyter_kite.egg-info/requires.txt
jupyter_kite.egg-info/top_level.txt
jupyter_kite/etc/jupyter-kite-serverextension.json
jupyter_kite/schema/__init__.py
jupyter_kite/schema/schema.json
jupyter_kite/specs/__init__.py
jupyter_kite/specs/base.py
jupyter_kite/specs/kitels.py
jupyter_kite/specs/utils.py
jupyter_kite/specs/config/__init__.py
jupyter_kite/specs/config/bash-language-server.schema.json
jupyter_kite/specs/config/dockerfile-language-server-nodejs.schema.json
jupyter_kite/specs/config/pyls.schema.json
jupyter_kite/specs/config/yaml-language-server.schema.json
jupyter_kite/tests/__init__.py
jupyter_kite/tests/conftest.py
jupyter_kite/tests/listener.py
jupyter_kite/tests/test_bad_spec.py
jupyter_kite/tests/test_detect.py
jupyter_kite/tests/test_extension.py
jupyter_kite/tests/test_listener.py
jupyter_kite/tests/test_paths.py
jupyter_kite/tests/test_session.py
jupyter_kite/tests/test_virtual_documents_shadow.py