Metadata-Version: 2.1
Name: jupyter-kite
Version: 2.0.2
Summary: Multi-Language Server WebSocket proxy for JupyterLab server.
Home-page: https://github.com/kiteco/jupyterlab-kite
Author: Kite
Author-email: support@kite.com
License: UNKNOWN
Keywords: Interactive,Language Server,LSP
Platform: UNKNOWN
Classifier: Framework :: Jupyter
Classifier: Intended Audience :: Developers
Classifier: Intended Audience :: Information Technology
Classifier: Programming Language :: Python
Requires-Python: >=3.6
